deploy_4_developer/cli/__init__.py
deploy_4_developer/cli/deploy.py
deploy_4_developer/cli/logger_init.py
deploy_4_developer/cli/sys_util.py
deploy_4_developer-0.0.4.dist-info/METADATA
deploy_4_developer-0.0.4.dist-info/WHEEL
deploy_4_developer-0.0.4.dist-info/entry_points.txt
deploy_4_developer-0.0.4.dist-info/licenses/LICENSE
deploy_4_developer-0.0.4.dist-info/RECORD
