Metadata-Version: 2.3
Name: deploy-4-developer
Version: 0.0.4
Summary: An open-source tool for developers to automate deployment tasks, including file uploads and remote command execution.
Project-URL: Homepage, https://github.com/Byte-Biscuit/deploy-4-developer
Project-URL: Repository, https://github.com/Byte-Biscuit/deploy-4-developer
Project-URL: Bug Tracker, https://github.com/Byte-Biscuit/deploy-4-developer/issues
Author-email: Biscuit Zhou <biscuit_zhou@outlook.com>
Classifier: License :: OSI Approved :: MIT License
Classifier: Operating System :: OS Independent
Classifier: Programming Language :: Python :: 3
Requires-Python: >=3.10.14
Requires-Dist: paramiko>=4.0.0
Requires-Dist: pyinstaller>=6.16.0
